pydag/__init__.py
pydag/cli.py
pydag/environments.py
pydag/exceptions.py
pydag/executor.py
pydag/helper.py
pydag/job.py
pydag/log.py
pydag/task.py
pydag/utils.py
pydag2-0.2.0.dist-info/LICENSE
pydag2-0.2.0.dist-info/METADATA
pydag2-0.2.0.dist-info/WHEEL
pydag2-0.2.0.dist-info/entry_points.txt
pydag2-0.2.0.dist-info/top_level.txt
pydag2-0.2.0.dist-info/RECORD
